{
    "configurations": [
        {
            "name": "UE5_RPG_VFXEditor Editor Win64 Development (UE5_RPG_VFX)",
            "compilerPath": "C:\\Program Files\\Microsoft Visual Studio\\2022\\Community\\VC\\Tools\\MSVC\\14.35.32215\\bin\\Hostx64\\x64\\cl.exe",
            "cStandard": "c17",
            "cppStandard": "c++17",
            "intelliSenseMode": "msvc-x64",
            "configurationProvider": "epic.ue",
            "compileCommands": "E:\\VFX_project\\UE5_RPG_VFX\\.vscode\\compileCommands_UE5_RPG_VFX.json"
        },
        {
            "name": "Win32",
            "compilerPath": "C:\\Program Files\\Microsoft Visual Studio\\2022\\Community\\VC\\Tools\\MSVC\\14.35.32215\\bin\\Hostx64\\x64\\cl.exe",
            "cStandard": "c17",
            "cppStandard": "c++17",
            "intelliSenseMode": "msvc-x64",
            "configurationProvider": "epic.ue",
            "compileCommands": "E:\\VFX_project\\UE5_RPG_VFX\\.vscode\\compileCommands_Default.json"
        }
    ],
    "version": 4
}